LICENSE.txt
MANIFEST.in
README.md
setup.py
cmsplugin_seocheck/__init__.py
cmsplugin_seocheck/cms_toolbar.py
cmsplugin_seocheck/urls.py
cmsplugin_seocheck/views.py
cmsplugin_seocheck.egg-info/PKG-INFO
cmsplugin_seocheck.egg-info/SOURCES.txt
cmsplugin_seocheck.egg-info/dependency_links.txt
cmsplugin_seocheck.egg-info/requires.txt
cmsplugin_seocheck.egg-info/top_level.txt
cmsplugin_seocheck/locale/de/LC_MESSAGES/django.mo
cmsplugin_seocheck/locale/de/LC_MESSAGES/django.po
cmsplugin_seocheck/static/cmsplugin_seocheck/bower_components/font-awesome/css/font-awesome.css
cmsplugin_seocheck/static/cmsplugin_seocheck/bower_components/font-awesome/css/font-awesome.min.css
cmsplugin_seocheck/static/cmsplugin_seocheck/bower_components/font-awesome/fonts/FontAwesome.otf
cmsplugin_seocheck/static/cmsplugin_seocheck/bower_components/font-awesome/fonts/fontawesome-webfont.eot
cmsplugin_seocheck/static/cmsplugin_seocheck/bower_components/font-awesome/fonts/fontawesome-webfont.svg
cmsplugin_seocheck/static/cmsplugin_seocheck/bower_components/font-awesome/fonts/fontawesome-webfont.ttf
cmsplugin_seocheck/static/cmsplugin_seocheck/bower_components/font-awesome/fonts/fontawesome-webfont.woff
cmsplugin_seocheck/static/cmsplugin_seocheck/bower_components/font-awesome/scss/_animated.scss
cmsplugin_seocheck/static/cmsplugin_seocheck/bower_components/font-awesome/scss/_bordered-pulled.scss
cmsplugin_seocheck/static/cmsplugin_seocheck/bower_components/font-awesome/scss/_core.scss
cmsplugin_seocheck/static/cmsplugin_seocheck/bower_components/font-awesome/scss/_fixed-width.scss
cmsplugin_seocheck/static/cmsplugin_seocheck/bower_components/font-awesome/scss/_icons.scss
cmsplugin_seocheck/static/cmsplugin_seocheck/bower_components/font-awesome/scss/_larger.scss
cmsplugin_seocheck/static/cmsplugin_seocheck/bower_components/font-awesome/scss/_list.scss
cmsplugin_seocheck/static/cmsplugin_seocheck/bower_components/font-awesome/scss/_mixins.scss
cmsplugin_seocheck/static/cmsplugin_seocheck/bower_components/font-awesome/scss/_path.scss
cmsplugin_seocheck/static/cmsplugin_seocheck/bower_components/font-awesome/scss/_rotated-flipped.scss
