Metadata-Version: 1.1
Name: cmsplugin-seocheck
Version: 0.1.0.a1
Summary: A djangocms plugin to check your page's SEO properties
Home-page: https://github.com/creimers/cmsplugin_seocheck
Author: Christoph Reimers
Author-email: christoph@superservice-international.com
License: BSD License
Keywords: djangocms,django,SEO
Platform: UNKNOWN
Classifier: Operating System :: OS Independent
Classifier: Development Status :: 3 - Alpha
Classifier: Programming Language :: Python
Classifier: Framework :: Django
Classifier: Programming Language :: Python :: 2.7
Classifier: Programming Language :: Python :: 3.4
